educabiz/__init__.py
educabiz/client.py
educabiz/exceptions.py
educabiz/models/__init__.py
educabiz/models/home.py
educabiz/models/school_qrcodeinfo.py
educabiz-0.0.5.dist-info/LICENSE
educabiz-0.0.5.dist-info/METADATA
educabiz-0.0.5.dist-info/WHEEL
educabiz-0.0.5.dist-info/entry_points.txt
educabiz-0.0.5.dist-info/top_level.txt
educabiz-0.0.5.dist-info/RECORD
