Metadata-Version: 2.1
Name: educabiz
Version: 0.0.5
Summary: API client for *.educabiz.com 
Author-email: Filipe Pina <shelf-corncob-said@duck.com>
Project-URL: Homepage, https://github.com/fopina/python-educabiz
Requires-Python: >=3.10
License-File: LICENSE
Requires-Dist: requests
Requires-Dist: pydantic
